README.md
setup.py
cainiao/__init__.py
cainiao/clients.py
cainiao/cloudprint.py
cainiao/errors.py
cainiao/logger.py
cainiao/templates.py
cainiao/waybill.py
cainiao.egg-info/PKG-INFO
cainiao.egg-info/SOURCES.txt
cainiao.egg-info/dependency_links.txt
cainiao.egg-info/requires.txt
cainiao.egg-info/top_level.txt
cainiao.egg-info/zip-safe