Metadata-Version: 2.1
Name: cainiao
Version: 0.2.0
Summary: Cainiao Waybill SDK.
Home-page: https://github.com/shengurun/cainiao
Author: shengurun
Author-email: shengurun@gmail.com
License: MIT
Platform: UNKNOWN
Classifier: Development Status :: 5 - Production/Stable
Classifier: Intended Audience :: Developers
Classifier: License :: OSI Approved :: MIT License
Classifier: Programming Language :: Python :: 3.7
Classifier: Programming Language :: Python :: 3.8
